{
  "$schema": "https://turbo.build/schema.json",
  "globalDependencies": [".env"],
  "globalEnv": [
    "LOG_LEVEL",
    "NODE_ENV",
    "NEXT_PUBLIC_LIBRARY_URL",
    "NEXT_PUBLIC_HOME_SITE_URL",
    "BLOG_API_URL",
    "NEXT_PUBLIC_BLOG_SITE_URL",
    "ADMIN_USERNAME",
    "ADMIN_PASSWORD",
    "SESSION_SECRET",
    "CONFIG_PATH",
    "REVALIDATE_SECRET",
    "STAGING_MODE",
    "OTEL_EXPORTER_OTLP_ENDPOINT",
    "PHOTOS_API_URL",
    "NEXT_PUBLIC_PHOTOS_SITE_URL",
    "MANAGE_USERNAME",
    "MANAGE_PASSWORD",
    "MANAGE_SESSION_SECRET",
    "RTK_API_URL",
    "NEXT_PUBLIC_RTK_SITE_URL"
  ],
  "tasks": {
    "build": {
      "dependsOn": ["^build"],
      "outputs": [".next/**", "!.next/cache/**"]
    },
    "lint": {},
    "dev": {
      "cache": false,
      "persistent": true
    }
  }
}
